filereport/__init__.py
filereport/block.py
filereport/plotly_utils.py
filereport/templates/base.html
filereport/templates/index.html
filereport/templates/style.css
filereport-0.1.1.dist-info/METADATA
filereport-0.1.1.dist-info/WHEEL
filereport-0.1.1.dist-info/top_level.txt
filereport-0.1.1.dist-info/RECORD
