Metadata-Version: 2.1
Name: filereport
Version: 0.1.1
Summary: HTML generator
Home-page: https://github.com/GaetanDesrues/filereport
Author: Gaetan Desrues
Author-email: gdesrues@gmail.com
License: UNKNOWN
Platform: UNKNOWN
Classifier: Programming Language :: Python :: 3
Classifier: License :: OSI Approved :: MIT License
Classifier: Operating System :: OS Independent
Requires-Dist: treefiles
Requires-Dist: markdown
Requires-Dist: htmlmin
Requires-Dist: plotly
Requires-Dist: jinja2
